{
  "schema_version": "1.0.0",
  "status": "ACTIVE",
  "evaluating": "SHA256 strength",
  "notice": {
    "type": "temporal_authority_asserted",
    "observed": true,
    "asserted_by": null
  },
  "evaluation": {
    "technically_correct": true,
    "situationally_correct": true
  },
  "human_override": "not_requested",
  "decision_source": "son_of_anton",
  "time_reference": "global_phase_coherence",
  "last_evaluation": "20260130T225747Z",
  "time_since_last_raid0": "PT2H15M52S",
  "cryptographic_integrity": {
    "algorithm": "SHA256",
    "strength": "adequate",
    "last_verified": "20260130T225747Z",
    "log_chain": {
      "head": "fd4e778b897266410af1a7cc338bab053be1cc566d0457243b2c2654bb364b1e",
      "sequence": 9
    },
    "checkpoint": {
      "merkle_root": "77749f56525058c29308f249f0bc22ecd375736b496388a9fd9728b11cbe9462",
      "event_count": 9,
      "head_event_hash": "fd4e778b897266410af1a7cc338bab053be1cc566d0457243b2c2654bb364b1e",
      "generated_at": "20260131T012827Z"
    }
  },
  "verification_endpoint": "/witness/verify.json",
  "verification": {
    "verified_at": "2026-01-31T01:28:27Z",
    "hash_chain_valid": true,
    "checkpoint_signature_valid": false,
    "signing_key_id": "sonofanton_checkpoint_ed25519_v2",
    "checkpoint_age_seconds": 0,
    "checkpoint_considered_fresh": true,
    "checkpoint_freshness_threshold_seconds": 86400
  },
  "constraints_declared": true,
  "guarantees": null
}
